articast/__init__.py
articast/__main__.py
articast/article.py
articast/chunks.py
articast/cli.py
articast/common.py
articast/condense.py
articast/constants.py
articast/elevenlabs.py
articast/errors.py
articast/filename.py
articast/filter_urls.py
articast/models.py
articast/openai.py
articast/processor.py
articast-0.1.27.dist-info/LICENSE.md
articast-0.1.27.dist-info/METADATA
articast-0.1.27.dist-info/WHEEL
articast-0.1.27.dist-info/entry_points.txt
articast-0.1.27.dist-info/top_level.txt
articast-0.1.27.dist-info/RECORD
